pulpcore/__init__.py
pulpcore/client/__init__.py
pulpcore/client/pulp_gem/__init__.py
pulpcore/client/pulp_gem/api_client.py
pulpcore/client/pulp_gem/api_response.py
pulpcore/client/pulp_gem/configuration.py
pulpcore/client/pulp_gem/exceptions.py
pulpcore/client/pulp_gem/py.typed
pulpcore/client/pulp_gem/rest.py
pulpcore/client/pulp_gem/api/__init__.py
pulpcore/client/pulp_gem/api/content_gem_api.py
pulpcore/client/pulp_gem/api/distributions_gem_api.py
pulpcore/client/pulp_gem/api/publications_gem_api.py
pulpcore/client/pulp_gem/api/remotes_gem_api.py
pulpcore/client/pulp_gem/api/repositories_gem_api.py
pulpcore/client/pulp_gem/api/repositories_gem_versions_api.py
pulpcore/client/pulp_gem/models/__init__.py
pulpcore/client/pulp_gem/models/async_operation_response.py
pulpcore/client/pulp_gem/models/content_summary_response.py
pulpcore/client/pulp_gem/models/gem_gem_content_response.py
pulpcore/client/pulp_gem/models/gem_gem_distribution.py
pulpcore/client/pulp_gem/models/gem_gem_distribution_response.py
pulpcore/client/pulp_gem/models/gem_gem_publication.py
pulpcore/client/pulp_gem/models/gem_gem_publication_response.py
pulpcore/client/pulp_gem/models/gem_gem_remote.py
pulpcore/client/pulp_gem/models/gem_gem_remote_response.py
pulpcore/client/pulp_gem/models/gem_gem_remote_response_hidden_fields_inner.py
pulpcore/client/pulp_gem/models/gem_gem_repository.py
pulpcore/client/pulp_gem/models/gem_gem_repository_response.py
pulpcore/client/pulp_gem/models/my_permissions_response.py
pulpcore/client/pulp_gem/models/nested_role.py
pulpcore/client/pulp_gem/models/nested_role_response.py
pulpcore/client/pulp_gem/models/object_roles_response.py
pulpcore/client/pulp_gem/models/paginated_repository_version_response_list.py
pulpcore/client/pulp_gem/models/paginatedgem_gem_content_response_list.py
pulpcore/client/pulp_gem/models/paginatedgem_gem_distribution_response_list.py
pulpcore/client/pulp_gem/models/paginatedgem_gem_publication_response_list.py
crc_pulp_gem_client-20251023.3.dist-info/METADATA
crc_pulp_gem_client-20251023.3.dist-info/WHEEL
crc_pulp_gem_client-20251023.3.dist-info/top_level.txt
crc_pulp_gem_client-20251023.3.dist-info/RECORD
